{"version":1,"resource":"file:///Users/canyonwan/Documents/code.aliyun/enforce-web/src/views/cause-library/manage/components/components/group-details/base-attr/save-base-attr.tsx","entries":[{"id":"L5SX.tsx","source":"Workspace Edit","timestamp":1656319213020},{"id":"jIEv.tsx","source":"Workspace Edit","timestamp":1656572552046},{"id":"x5GM.tsx","source":"moved.source","timestamp":1656579346981},{"id":"dE3X.tsx","timestamp":1656923566096},{"id":"0tHn.tsx","timestamp":1656923617772},{"id":"ywJO.tsx","source":"Fix all ESLint auto-fixable problems","timestamp":1656923641522},{"id":"91gd.tsx","timestamp":1656923657287},{"id":"eVaX.tsx","timestamp":1656923717005},{"id":"Eo0F.tsx","timestamp":1656923754547},{"id":"Ipqs.tsx","timestamp":1656923835580},{"id":"5PtM.tsx","source":"searchReplace.source","timestamp":1658889398285}]}