{"version":1,"resource":"file:///Users/canyonwan/Documents/code.aliyun/enforce-web/src/views/unit-test/todo.test.ts","entries":[{"id":"RwZH.ts","timestamp":1652157710708},{"id":"uXfs.ts","timestamp":1652157722931},{"id":"RdS5.ts","timestamp":1652157744746},{"id":"OvEG.ts","timestamp":1652158131131},{"id":"ToRH.ts","timestamp":1652161370903},{"id":"Of5S.ts","timestamp":1652161399584},{"id":"p43m.ts","timestamp":1652161417889},{"id":"T9YR.ts","timestamp":1652163837914},{"id":"XeFa.ts","timestamp":1652163857042},{"id":"NF0N.ts","source":"renamed.source","timestamp":1652164277464},{"id":"pDoQ.ts","timestamp":1652164298059},{"id":"VHwh.ts","timestamp":1652164510198},{"id":"UVvW.ts","source":"Fix all ESLint auto-fixable problems","timestamp":1652164854244},{"id":"A4Fb.ts","timestamp":1652165865836},{"id":"pfTF.ts","source":"Fix all ESLint auto-fixable problems","timestamp":1652165888379}]}