{"version":1,"resource":"file:///Users/canyonwan/Documents/code.aliyun/enforce-web/src/views/program/components/columns.ts","entries":[{"id":"veI2.ts","timestamp":1651201650490},{"id":"lheH.ts","source":"moved.source","timestamp":1651201734782},{"id":"Mov4.ts","source":"searchReplace.source","timestamp":1651228023162},{"id":"FJQN.ts","timestamp":1651228043368},{"id":"nQJP.ts","timestamp":1651228077342},{"id":"lW1r.ts","timestamp":1651228089419},{"id":"h80O.ts","timestamp":1652840027990},{"id":"VNfq.ts","source":"从“./map-options”添加导入","timestamp":1652943427261},{"id":"lxmD.ts","timestamp":1652943504614},{"id":"2Lcc.ts","timestamp":1652943516878},{"id":"Eo1s.ts","source":"undoRedo.source","timestamp":1652943524981},{"id":"q57m.ts","timestamp":1658818289522},{"id":"bw18.ts","timestamp":1658818369545},{"id":"jS0k.ts","source":"Fix all fixable ESLint issues","timestamp":1658818429894},{"id":"AA07.ts","source":"Fix all fixable ESLint issues","timestamp":1658818724436},{"id":"VhPP.ts","source":"Fix all fixable ESLint issues","timestamp":1658818758240},{"id":"jvJ3.ts","timestamp":1658818938108},{"id":"lk31.ts","source":"Fix all fixable ESLint issues","timestamp":1658819177718},{"id":"KJRx.ts","timestamp":1658819241239},{"id":"K2Go.ts","timestamp":1658819291632},{"id":"j560.ts","timestamp":1658819400457},{"id":"adJ0.ts","timestamp":1658819721049},{"id":"W4Kj.ts","timestamp":1658819754703},{"id":"O2NJ.ts","timestamp":1658819765889},{"id":"EIyK.ts","timestamp":1658820429491},{"id":"9Eu5.ts","timestamp":1658820761912},{"id":"XZA6.ts","source":"Fix all fixable ESLint issues","timestamp":1658820766288},{"id":"kMcE.ts","timestamp":1658820789740},{"id":"bfUH.ts","source":"Fix all fixable ESLint issues","timestamp":1658821910880},{"id":"aiaE.ts","timestamp":1658821928007},{"id":"R8ap.ts","source":"Fix all fixable ESLint issues","timestamp":1658821931882},{"id":"mKBh.ts","timestamp":1658821948290},{"id":"igt4.ts","source":"Fix all fixable ESLint issues","timestamp":1658821977690},{"id":"Laib.ts","timestamp":1658822809082},{"id":"xzng.ts","source":"Fix all fixable ESLint issues","timestamp":1658822921499},{"id":"udCJ.ts","source":"Fix all fixable ESLint issues","timestamp":1658822948899},{"id":"jm84.ts","source":"Fix all fixable ESLint issues","timestamp":1658823000965},{"id":"7u1u.ts","source":"Fix all fixable ESLint issues","timestamp":1658823015374},{"id":"fQc2.ts","timestamp":1658823067812},{"id":"aSNC.ts","timestamp":1658823150170},{"id":"kwim.ts","timestamp":1658823162936},{"id":"L2VE.ts","timestamp":1658823367316},{"id":"iKRe.ts","source":"Fix all fixable ESLint issues","timestamp":1658823378627},{"id":"BpBu.ts","timestamp":1658823385452},{"id":"zRjQ.ts","source":"Fix all fixable ESLint issues","timestamp":1659062635486},{"id":"7PqS.ts","timestamp":1659062687799},{"id":"UL9R.ts","timestamp":1659062712908},{"id":"FROv.ts","timestamp":1659062761256},{"id":"y0Gj.ts","timestamp":1659062859673},{"id":"ADU1.ts","timestamp":1659062884900}]}