{"version":1,"resource":"file:///Users/canyonwan/Documents/gitee.com/develop/vms-app/src/api/goods/types.ts","entries":[{"id":"Stwp.ts","source":"Fix all ESLint auto-fixable problems","timestamp":1650637346853},{"id":"xW9u.ts","source":"Fix all ESLint auto-fixable problems","timestamp":1650637585646},{"id":"0KmT.ts","source":"Fix all ESLint auto-fixable problems","timestamp":1650637628090},{"id":"aEgR.ts","source":"Fix all ESLint auto-fixable problems","timestamp":1650638309413},{"id":"HSqM.ts","source":"Fix all ESLint auto-fixable problems","timestamp":1650638338649},{"id":"dbGB.ts","timestamp":1650638372305},{"id":"yZ66.ts","timestamp":1650640877420},{"id":"sybK.ts","source":"Fix all ESLint auto-fixable problems","timestamp":1650641668135},{"id":"thBH.ts","timestamp":1650641739445},{"id":"bWdM.ts","timestamp":1650641772776}]}