{"version":1,"resource":"file:///Users/canyonwan/Documents/code.aliyun/enforce-web/src/views/cause-library/discretion/group/index.tsx","entries":[{"id":"ZGBB.tsx","timestamp":1654852492763},{"id":"D3Mo.tsx","source":"Fix all ESLint auto-fixable problems","timestamp":1654852502503},{"id":"VgK3.tsx","timestamp":1654852512103},{"id":"jfxy.tsx","timestamp":1654852535893},{"id":"qG2f.tsx","timestamp":1654852548688},{"id":"nyQd.tsx","timestamp":1654852572389},{"id":"Rjfh.tsx","timestamp":1654852594200},{"id":"1edG.tsx","timestamp":1654852743385},{"id":"G7at.tsx","source":"undoRedo.source","timestamp":1654852753978}]}